rcdb_web/__init__.py
rcdb_web/pagination.py
rcdb_web/run_table.py
rcdb_web/conditions/__init__.py
rcdb_web/conditions/views.py
rcdb_web/files/__init__.py
rcdb_web/files/views.py
rcdb_web/logs/__init__.py
rcdb_web/logs/views.py
rcdb_web/runs/__init__.py
rcdb_web/runs/views.py
rcdb_web/statistics/__init__.py
rcdb_web/statistics/views.py
rcdb_web-0.9.1.dist-info/METADATA
rcdb_web-0.9.1.dist-info/WHEEL
rcdb_web-0.9.1.dist-info/entry_points.txt
rcdb_web-0.9.1.dist-info/top_level.txt
rcdb_web-0.9.1.dist-info/RECORD
