Metadata-Version: 2.1
Name: rcdb-web
Version: 0.9.1
Summary: RCDB Web - Run Conditions DataBase web interface
Home-page: https://github.com/JeffersonLab/rcdb
Author: Dmitry Romanov
Author-email: romanov@jlab.org
License: MIT
Classifier: Development Status :: 4 - Beta
Classifier: License :: OSI Approved :: MIT License
Classifier: Programming Language :: Python :: 3
Classifier: Programming Language :: Python :: 3.6
Classifier: Programming Language :: Python :: 3.7
Classifier: Programming Language :: Python :: 3.8
Classifier: Programming Language :: Python :: 3.9
Classifier: Programming Language :: Python :: 3.10
Requires-Dist: rcdb
Requires-Dist: flask
